LICENSE
README.md
setup.py
generate/__init__.py
generate/project.py
test/__init__.py
test/context.py
test/test_module.py
woolang_project_generator.egg-info/PKG-INFO
woolang_project_generator.egg-info/SOURCES.txt
woolang_project_generator.egg-info/dependency_links.txt
woolang_project_generator.egg-info/top_level.txt