Metadata-Version: 2.1
Name: woolang-project-generator
Version: 4.0.0
Summary: The project generator for woolang
Home-page: https://github.com/woo-lang/woolang-project-generator
Author: P Pranav Baburaj
Author-email: code-roller@googlegroups.com
License: UNKNOWN
Platform: UNKNOWN
Classifier: Programming Language :: Python :: 3
Classifier: License :: OSI Approved :: MIT License
Classifier: Operating System :: OS Independent
Requires-Python: >=3.6
